{
  "quizTitle": "Наслов на квиз",
  "quizDescription": "Опис на квизот (изборно)",
  "enterTheQuestion": "Напишете го прашањето",
  "option": "Внесете го вашиот избор {0}",
  "dueIn": " Со рок до {0} {1}",
  "addMoreOptions": "Додај опција",
  "choices": "Избори",
  "checkMe": "Штиклирај ако е точно",
  "check": "Провери",
  "next": "Следно",
  "prev": "Претходно",
  "done": "Готово",
  "back": "Назад",
  "required": "Задолжително",
  "aggregrateResult": "Збирен резултат",
  "addQuestion": "Додај прашање",
  "coverImage": "Насловна слика (изборно)",
  "clear": "Исчисти",
  "invalidFileFormat": "Форматот на датотеката е неважечки",
  "uploadCoverImage": "Постави насловна слика",
  "dueBy": "Краен рок до",
  "resultVisibleTo": "Резултатите се видливи за",
  "resultEveryone": "Резултатите се видливи за сите",
  "resultMe": "Резултатите се видливи само за мене",
  "correctAnswer": "{0} Точен одговор прикажан по секое прашање",
  "everyone": "Сите",
  "onlyMe": "Само јас",
  "invalidDateTime": "Предупреди! Неважечки датум или време. Мора да биде поголем од тековните датум и време.",
  "sureDeleteThis": "Сигурно ли сакате да избришете?",
  "ok": "ОК",
  "cancel": "Откажи",
  "forQuizAtleastOneQuestion": "Потребно е барем едно прашање",
  "alreadyAttempted": "Веќе се обидовте со овој квиз",
  "maxTenOption": "Максимално се дозволени 10 опции за прашање",
  "atLeastTwoOptionsRequired": "Потребни се најмалку две опции",
  "questionLeftBlank": "Прашањето не може да се остави празно",
  "selectCorrectChoice": "Изберете правилен избор за прашањето",
  "showCorrectAnswer": "Прикажи точен одговор по секое прашање",
  "answerCannotChange": "Одговорот не може да се промени ако е избрана оваа опција",
  "question": "Прашање",
  "questions": "Прашања",
  "question_numbers": "Прашања: {0}",
  "totalQuestionQuiz": "Вкупно {0} {1} во квизот",
  "alreadyTired": "Белешка - веќе го имате направено овој квиз!",
  "notConsideredFinalScore": "Можете повторно да се обидете со овој квиз за вежбање. Вашиот резултат за овој обид не би се сметал за краен резултат.",
  "start": "Започни",
  "xofy": "{0} од {1}",
  "note": "Белешка!",
  "choose_any_choice": "Одговорете пред да преминете на следното прашање",
  "continue": "Продолжи",
  "answer_response": "Одговор на одговорот",
  "correct": "Точно",
  "your_answer": "Вашиот одговор",
  "incorrect": "Неточно",
  "correct_answer": "Точен одговор",
  "your_answer_is": "Вашиот одговор е",
  "right_answer_is": "Десниот одговор е",
  "submit": "Поднеси",
  "quiz_summary": "Резиме на квиз",
  "quiz_expired": "Квизот е истечен...",
  "expired_on": "Истечено на",
  "participation": "Учество {0}%",
  "xofy_people_responded": "Одговорија {0} од {1} луѓе",
  "you_responded": "Одговоривте",
  "score": "Резултат {0}",
  "you_yet_respond": "Сѐ уште не сте одговориле",
  "responders": "Испитаници",
  "non_responders": "Испитаници што не одговориле",
  "you": "Вие",
  "respond": "Одговори",
  "view_result": "Прикажи ги резултатите",
  "be_the_first_one_to_respond": "Први одговорете на квизот",
  "one_responded": "{0} одговори",
  "two_responded": "{0} и {1} одговорија",
  "three_responded": "{0}, {1} и {2} одговорија",
  "three_and_one_other_responded": "{0}, {1}, {2} и уште 1 друг одговорија",
  "three_and_others_responded": "{0}, {1}, {2} и {3} други одговорија",
  "due_by_date": "Крајниот рок е до {0}",
  "result_everyone": "Одговорите се видливи за сите",
  "result_creator": "Резултатите се видливи само за мене",
  "close": "Затвори",
  "changeDueBy": "Измени го крајниот рок",
  "closeQuiz": "Затвори квиз",
  "deleteQuiz": "Избриши го квизот",
  "download": "Преземи",
  "downloadImage": "Преземи ја сликата",
  "downloadCSV": "Преземи CSV",
  "confirm": "Потврди",
  "closeQuizConfirm": "Дали сигурно сакате да го затворите овој квиз?",
  "deleteQuizConfirm": "Дали сигурно сакате да се избрише овој квиз?",
  "change": "Измени",
  "changeDueDate": "Измени го крајниот датум",
  "nWeek": "{0} седмица",
  "hours": "часа",
  "hour": "час",
  "minutes": "минути",
  "minute": "минута",
  "days": "дена",
  "day": "ден",
  "daysCalendar": "понеделник, вторник, среда, четврток, петок, сабота, недела",
  "daysShortCalendar": "пон, вто, сре, чет, пет, саб, нед",
  "daysMinCalendar": "не, по, вт, ср, че, пе, са",
  "monthsCalendar": "јануари, февруари, март, април, мај, јуни, јули, август, септември, октомври, ноември, декември",
  "monthsShortCalendar": "јан, фев, мар, апр, мај, јун, јул, авг, сеп, окт, ное, дек",
  "todayCalendar": "Денес",
  "monthsTitleCalendar": "Месеци",
  "clearCalendar": "Исчисти",
  "$manifest.composeExtensions[0].commands[0].taskInfo.title": "Квиз",
  "$manifest.composeExtensions[0].commands[0].title": "Квиз",
  "$manifest.description": "Создај нов квиз",
  "$manifest.name": "Квиз",
  "$manifest.activities.activityTypes[0].description": "Известување со потсетник за квиз",
  "$manifest.activities.activityTypes[1].description": "Некои одговори на вашиот квиз",
  "$manifest.activities.activityTypes[2].description": "Дневен преглед на статусот на одговор на квиз",
  "$manifest.activities.activityTypes[3].description": "Резултатите од квизот се објавени",
  "$manifest.msTeamsProps.name.full": "Квиз",
  "$manifest.msTeamsProps.name.short": "Квиз",
  "$manifest.msTeamsProps.description.full": "Создајте квиз за да го тестирате знаењето на луѓето во муабет или канал. Најдете ја апликацијата во „…“ под полето за составување пораки. Обезбедете наслов и создајте прашалник за да го објавите во вашиот муабет или канал. Најдете одговори и сумирано резиме за брза проценка.",
  "$manifest.msTeamsProps.description.short": "Создај квиз"
}